LICENSE
README.md
setup.py
rickrolldetector/Rickrolldetector.py
rickrolldetector/__init__.py
rickrolldetector.egg-info/PKG-INFO
rickrolldetector.egg-info/SOURCES.txt
rickrolldetector.egg-info/dependency_links.txt
rickrolldetector.egg-info/requires.txt
rickrolldetector.egg-info/top_level.txt