Metadata-Version: 2.1
Name: rickrolldetector
Version: 0.1.3
Summary: A module made for rickroll protection
Home-page: https://github.com/Sengolda/rickrolldetector
Author: Sengolda
License: MIT
Platform: UNKNOWN
